Pegaflow-5.0.4.data/scripts/pegaflow_monitor
pegaflow/DAX3.py
pegaflow/Workflow.py
pegaflow/__init__.py
pegaflow/braindump.py
pegaflow/cluster.py
pegaflow/command.py
pegaflow/exitcode.py
pegaflow/init-old.py
pegaflow/init.py
pegaflow/json.py
pegaflow/kickstart.py
pegaflow/properties.py
pegaflow/replica_catalog.py
pegaflow/s3.py
pegaflow/site_catalog.py
pegaflow/submitdir.py
pegaflow/transformation_catalog.py
pegaflow/user.py
pegaflow/workflow.py
pegaflow/yaml.py
pegaflow/api/__init__.py
pegaflow/api/_utils.py
pegaflow/api/errors.py
pegaflow/api/mixins.py
pegaflow/api/properties.py
pegaflow/api/replica_catalog.py
pegaflow/api/site_catalog.py
pegaflow/api/transformation_catalog.py
pegaflow/api/workflow.py
pegaflow/api/writable.py
pegaflow/catalogs/__init__.py
pegaflow/catalogs/replica_catalog.py
pegaflow/catalogs/sites_catalog.py
pegaflow/catalogs/transformation_catalog.py
pegaflow/cli/__init__.py
pegaflow/cli/pegasus-analyzer.py
pegaflow/cli/pegasus-config.py
pegaflow/cli/pegasus-cwl-converter.py
pegaflow/cli/pegasus-dagman.py
pegaflow/cli/pegasus-db-admin.py
pegaflow/cli/pegasus-em.py
pegaflow/cli/pegasus-exitcode.py
pegaflow/cli/pegasus-globus-online-init.py
pegaflow/cli/pegasus-globus-online.py
pegaflow/cli/pegasus-graphviz.py
pegaflow/cli/pegasus-init.py
pegaflow/cli/pegasus-integrity.py
pegaflow/cli/pegasus-metadata.py
pegaflow/cli/pegasus-monitord.py
pegaflow/cli/pegasus-preflight-check.py
pegaflow/cli/pegasus-remove.py
pegaflow/cli/pegasus-run.py
pegaflow/cli/pegasus-s3.py
pegaflow/cli/pegasus-service.py
pegaflow/cli/pegasus-statistics.py
pegaflow/cli/pegasus-submitdir.py
pegaflow/cli/pegasus-transfer.py
pegaflow/client/__init__.py
pegaflow/client/_client.py
pegaflow/db/__init__.py
pegaflow/db/base_loader.py
pegaflow/db/connection.py
pegaflow/db/dashboard_loader.py
pegaflow/db/ensembles.py
pegaflow/db/errors.py
pegaflow/db/expunge.py
pegaflow/db/schema.py
pegaflow/db/workflow_loader.py
pegaflow/db/admin/__init__.py
pegaflow/db/admin/admin_loader.py
Pegaflow-5.0.4.dist-info/LICENSE.txt
Pegaflow-5.0.4.dist-info/METADATA
Pegaflow-5.0.4.dist-info/WHEEL
Pegaflow-5.0.4.dist-info/top_level.txt
Pegaflow-5.0.4.dist-info/RECORD
