Metadata-Version: 2.1
Name: Pegaflow
Version: 5.0.4
Summary: An easy-to-use Python API for Pegasus 5.0
Home-page: https://github.com/polyactis/pegaflow
Author: Yu S. Huang
Author-email: polyactis@gmail.com
License: Apache2
Keywords: scientific workflows
Platform: UNKNOWN
Classifier: Development Status :: 5 - Production/Stable
Classifier: Intended Audience :: Developers
Classifier: Intended Audience :: Science/Research
Classifier: Operating System :: Unix
Classifier: Programming Language :: Python
Classifier: Programming Language :: Python :: 3
Classifier: Topic :: Scientific/Engineering
Classifier: Topic :: Utilities
Classifier: License :: OSI Approved :: Apache Software License
Requires-Python: >=3.5
